gauntlet/__init__.py
gauntlet/benchmark.py
gauntlet/challengers.py
gauntlet/configs.py
gauntlet/environments.py
gauntlet/utils.py
gauntlet_benchmark-0.1.3.dist-info/licenses/LICENSE
gauntlet_benchmark-0.1.3.dist-info/METADATA
gauntlet_benchmark-0.1.3.dist-info/WHEEL
gauntlet_benchmark-0.1.3.dist-info/top_level.txt
gauntlet_benchmark-0.1.3.dist-info/RECORD
