Metadata-Version: 2.4
Name: gauntlet-benchmark
Version: 0.1.3
Summary: A next-generation MARL evaluation framework for comprehensive robustness testing.
Author-email: Tanvish Desai <tanvishdesai.05@gmail.com>
License-Expression: MIT
Project-URL: Homepage, https://github.com/tanvishdesai/gauntlet-benchmark
Project-URL: Bug Tracker, https://github.com/tanvishdesai/gauntlet-benchmark/issues
Classifier: Programming Language :: Python :: 3
Classifier: Operating System :: OS Independent
Classifier: Intended Audience :: Science/Research
Classifier: Topic :: Scientific/Engineering :: Artificial Intelligence
Requires-Python: >=3.8
License-File: LICENSE
Requires-Dist: torch
Requires-Dist: numpy
Requires-Dist: gymnasium
Requires-Dist: hydra-core
Requires-Dist: omegaconf
Requires-Dist: matplotlib
Requires-Dist: seaborn
Requires-Dist: wandb
Provides-Extra: nash
Requires-Dist: nashpy; extra == "nash"
Provides-Extra: openspiel
Requires-Dist: open_spiel; extra == "openspiel"
Provides-Extra: pettingzoo
Requires-Dist: pettingzoo; extra == "pettingzoo"
Provides-Extra: dev
Requires-Dist: build; extra == "dev"
Requires-Dist: twine; extra == "dev"
Requires-Dist: pytest; extra == "dev"
Dynamic: license-file
